{
  "dpId": "5bf59019-9c78-4ca7-b901-23a5bf3d6663",
  "items": [
    "saga-robotics/strawberry-data/04132021_163324_grippercam_2.png"
  ],
  "name": "saga-robotics/strawberry-data/04132021_163324_grippercam_2.png",
  "createdByEmail": "sampleprojects@infolks.in",
  "labels": [
    {
      "category": [
        [
          "object",
          "flesh"
        ]
      ],
      "attributes": [],
      "labelid": "17562091-bdf6-4fdd-975f-d5cb6286ae06",
      "polygon": [
        {
          "xnorm": 0.38984375,
          "ynorm": 0.6125
        },
        {
          "xnorm": 0.39140625,
          "ynorm": 0.6072916666666667
        },
        {
          "xnorm": 0.39296875,
          "ynorm": 0.6010416666666667
        },
        {
          "xnorm": 0.39375,
          "ynorm": 0.5947916666666667
        },
        {
          "xnorm": 0.39453125,
          "ynorm": 0.5895833333333333
        },
        {
          "xnorm": 0.39453125,
          "ynorm": 0.584375
        },
        {
          "xnorm": 0.3953125,
          "ynorm": 0.5791666666666667
        },
        {
          "xnorm": 0.39609375,
          "ynorm": 0.5729166666666666
        },
        {
          "xnorm": 0.396875,
          "ynorm": 0.5677083333333334
        },
        {
          "xnorm": 0.39765625,
          "ynorm": 0.5614583333333333
        },
        {
          "xnorm": 0.3984375,
          "ynorm": 0.55625
        },
        {
          "xnorm": 0.39921875,
          "ynorm": 0.55
        },
        {
          "xnorm": 0.39921875,
          "ynorm": 0.5447916666666667
        },
        {
          "xnorm": 0.4,
          "ynorm": 0.5395833333333333
        },
        {
          "xnorm": 0.40078125,
          "ynorm": 0.5333333333333333
        },
        {
          "xnorm": 0.4015625,
          "ynorm": 0.528125
        },
        {
          "xnorm": 0.40234375,
          "ynorm": 0.5229166666666667
        },
        {
          "xnorm": 0.40390625,
          "ynorm": 0.5166666666666667
        },
        {
          "xnorm": 0.4046875,
          "ynorm": 0.5104166666666666
        },
        {
          "xnorm": 0.40546875,
          "ynorm": 0.5052083333333334
        },
        {
          "xnorm": 0.40546875,
          "ynorm": 0.5
        },
        {
          "xnorm": 0.4078125,
          "ynorm": 0.49375
        },
        {
          "xnorm": 0.409375,
          "ynorm": 0.4864583333333333
        },
        {
          "xnorm": 0.41015625,
          "ynorm": 0.48020833333333335
        },
        {
          "xnorm": 0.4109375,
          "ynorm": 0.475
        },
        {
          "xnorm": 0.4125,
          "ynorm": 0.46979166666666666
        },
        {
          "xnorm": 0.41328125,
          "ynorm": 0.46458333333333335
        },
        {
          "xnorm": 0.41328125,
          "ynorm": 0.459375
        },
        {
          "xnorm": 0.41328125,
          "ynorm": 0.453125
        },
        {
          "xnorm": 0.41328125,
          "ynorm": 0.4479166666666667
        },
        {
          "xnorm": 0.41328125,
          "ynorm": 0.4427083333333333
        },
        {
          "xnorm": 0.41484375,
          "ynorm": 0.43645833333333334
        },
        {
          "xnorm": 0.41640625,
          "ynorm": 0.43125
        },
        {
          "xnorm": 0.41796875,
          "ynorm": 0.42604166666666665
        },
        {
          "xnorm": 0.4203125,
          "ynorm": 0.421875
        },
        {
          "xnorm": 0.421875,
          "ynorm": 0.4166666666666667
        },
        {
          "xnorm": 0.42421875,
          "ynorm": 0.41041666666666665
        },
        {
          "xnorm": 0.42578125,
          "ynorm": 0.40520833333333334
        },
        {
          "xnorm": 0.428125,
          "ynorm": 0.4
        },
        {
          "xnorm": 0.4296875,
          "ynorm": 0.39479166666666665
        },
        {
          "xnorm": 0.43125,
          "ynorm": 0.38958333333333334
        },
        {
          "xnorm": 0.4328125,
          "ynorm": 0.384375
        },
        {
          "xnorm": 0.434375,
          "ynorm": 0.378125
        },
        {
          "xnorm": 0.4375,
          "ynorm": 0.3729166666666667
        },
        {
          "xnorm": 0.43984375,
          "ynorm": 0.36770833333333336
        },
        {
          "xnorm": 0.4421875,
          "ynorm": 0.36354166666666665
        },
        {
          "xnorm": 0.4453125,
          "ynorm": 0.36041666666666666
        },
        {
          "xnorm": 0.44765625,
          "ynorm": 0.35625
        },
        {
          "xnorm": 0.45078125,
          "ynorm": 0.35208333333333336
        },
        {
          "xnorm": 0.45390625,
          "ynorm": 0.34791666666666665
        },
        {
          "xnorm": 0.45703125,
          "ynorm": 0.34479166666666666
        },
        {
          "xnorm": 0.46015625,
          "ynorm": 0.3416666666666667
        },
        {
          "xnorm": 0.4625,
          "ynorm": 0.3375
        },
        {
          "xnorm": 0.46640625,
          "ynorm": 0.33541666666666664
        },
        {
          "xnorm": 0.471875,
          "ynorm": 0.3333333333333333
        },
        {
          "xnorm": 0.4765625,
          "ynorm": 0.33229166666666665
        },
        {
          "xnorm": 0.48046875,
          "ynorm": 0.3302083333333333
        },
        {
          "xnorm": 0.484375,
          "ynorm": 0.32916666666666666
        },
        {
          "xnorm": 0.490625,
          "ynorm": 0.328125
        },
        {
          "xnorm": 0.49453125,
          "ynorm": 0.328125
        },
        {
          "xnorm": 0.4984375,
          "ynorm": 0.32916666666666666
        },
        {
          "xnorm": 0.503125,
          "ynorm": 0.33125
        },
        {
          "xnorm": 0.50703125,
          "ynorm": 0.33229166666666665
        },
        {
          "xnorm": 0.51015625,
          "ynorm": 0.33541666666666664
        },
        {
          "xnorm": 0.5140625,
          "ynorm": 0.3385416666666667
        },
        {
          "xnorm": 0.5171875,
          "ynorm": 0.3416666666666667
        },
        {
          "xnorm": 0.5203125,
          "ynorm": 0.34479166666666666
        },
        {
          "xnorm": 0.52265625,
          "ynorm": 0.3489583333333333
        },
        {
          "xnorm": 0.52578125,
          "ynorm": 0.35208333333333336
        },
        {
          "xnorm": 0.528125,
          "ynorm": 0.3572916666666667
        },
        {
          "xnorm": 0.53125,
          "ynorm": 0.36041666666666666
        },
        {
          "xnorm": 0.53515625,
          "ynorm": 0.36354166666666665
        },
        {
          "xnorm": 0.53828125,
          "ynorm": 0.36770833333333336
        },
        {
          "xnorm": 0.54140625,
          "ynorm": 0.37083333333333335
        },
        {
          "xnorm": 0.5453125,
          "ynorm": 0.37395833333333334
        },
        {
          "xnorm": 0.5484375,
          "ynorm": 0.378125
        },
        {
          "xnorm": 0.55078125,
          "ynorm": 0.38333333333333336
        },
        {
          "xnorm": 0.553125,
          "ynorm": 0.38958333333333334
        },
        {
          "xnorm": 0.5546875,
          "ynorm": 0.39479166666666665
        },
        {
          "xnorm": 0.55703125,
          "ynorm": 0.39895833333333336
        },
        {
          "xnorm": 0.559375,
          "ynorm": 0.4041666666666667
        },
        {
          "xnorm": 0.56171875,
          "ynorm": 0.4083333333333333
        },
        {
          "xnorm": 0.56484375,
          "ynorm": 0.4125
        },
        {
          "xnorm": 0.565625,
          "ynorm": 0.41770833333333335
        },
        {
          "xnorm": 0.56796875,
          "ynorm": 0.42291666666666666
        },
        {
          "xnorm": 0.5703125,
          "ynorm": 0.4270833333333333
        },
        {
          "xnorm": 0.57265625,
          "ynorm": 0.4322916666666667
        },
        {
          "xnorm": 0.57421875,
          "ynorm": 0.4375
        },
        {
          "xnorm": 0.5765625,
          "ynorm": 0.4427083333333333
        },
        {
          "xnorm": 0.57890625,
          "ynorm": 0.446875
        },
        {
          "xnorm": 0.58046875,
          "ynorm": 0.45208333333333334
        },
        {
          "xnorm": 0.5828125,
          "ynorm": 0.45729166666666665
        },
        {
          "xnorm": 0.584375,
          "ynorm": 0.4625
        },
        {
          "xnorm": 0.58515625,
          "ynorm": 0.46770833333333334
        },
        {
          "xnorm": 0.58671875,
          "ynorm": 0.47291666666666665
        },
        {
          "xnorm": 0.58828125,
          "ynorm": 0.478125
        },
        {
          "xnorm": 0.58984375,
          "ynorm": 0.48333333333333334
        },
        {
          "xnorm": 0.59140625,
          "ynorm": 0.48854166666666665
        },
        {
          "xnorm": 0.59375,
          "ynorm": 0.49270833333333336
        },
        {
          "xnorm": 0.5953125,
          "ynorm": 0.4979166666666667
        },
        {
          "xnorm": 0.596875,
          "ynorm": 0.5041666666666667
        },
        {
          "xnorm": 0.59921875,
          "ynorm": 0.509375
        },
        {
          "xnorm": 0.6015625,
          "ynorm": 0.5145833333333333
        },
        {
          "xnorm": 0.603125,
          "ynorm": 0.5208333333333334
        },
        {
          "xnorm": 0.60546875,
          "ynorm": 0.5260416666666666
        },
        {
          "xnorm": 0.60703125,
          "ynorm": 0.53125
        },
        {
          "xnorm": 0.60859375,
          "ynorm": 0.5375
        },
        {
          "xnorm": 0.6109375,
          "ynorm": 0.5416666666666666
        },
        {
          "xnorm": 0.6125,
          "ynorm": 0.546875
        },
        {
          "xnorm": 0.6140625,
          "ynorm": 0.5520833333333334
        },
        {
          "xnorm": 0.61640625,
          "ynorm": 0.5572916666666666
        },
        {
          "xnorm": 0.61875,
          "ynorm": 0.5635416666666667
        },
        {
          "xnorm": 0.62109375,
          "ynorm": 0.5677083333333334
        },
        {
          "xnorm": 0.6234375,
          "ynorm": 0.5729166666666666
        },
        {
          "xnorm": 0.62578125,
          "ynorm": 0.5770833333333333
        },
        {
          "xnorm": 0.628125,
          "ynorm": 0.5822916666666667
        },
        {
          "xnorm": 0.63046875,
          "ynorm": 0.5875
        },
        {
          "xnorm": 0.6328125,
          "ynorm": 0.5916666666666667
        },
        {
          "xnorm": 0.63515625,
          "ynorm": 0.5958333333333333
        },
        {
          "xnorm": 0.63671875,
          "ynorm": 0.6010416666666667
        },
        {
          "xnorm": 0.6390625,
          "ynorm": 0.6052083333333333
        },
        {
          "xnorm": 0.63984375,
          "ynorm": 0.6104166666666667
        },
        {
          "xnorm": 0.64140625,
          "ynorm": 0.615625
        },
        {
          "xnorm": 0.64296875,
          "ynorm": 0.6208333333333333
        },
        {
          "xnorm": 0.6390625,
          "ynorm": 0.621875
        },
        {
          "xnorm": 0.63515625,
          "ynorm": 0.621875
        },
        {
          "xnorm": 0.63125,
          "ynorm": 0.621875
        },
        {
          "xnorm": 0.62734375,
          "ynorm": 0.621875
        },
        {
          "xnorm": 0.6234375,
          "ynorm": 0.621875
        },
        {
          "xnorm": 0.61953125,
          "ynorm": 0.621875
        },
        {
          "xnorm": 0.61484375,
          "ynorm": 0.621875
        },
        {
          "xnorm": 0.61015625,
          "ynorm": 0.621875
        },
        {
          "xnorm": 0.60546875,
          "ynorm": 0.621875
        },
        {
          "xnorm": 0.6015625,
          "ynorm": 0.621875
        },
        {
          "xnorm": 0.596875,
          "ynorm": 0.621875
        },
        {
          "xnorm": 0.59296875,
          "ynorm": 0.621875
        },
        {
          "xnorm": 0.58828125,
          "ynorm": 0.621875
        },
        {
          "xnorm": 0.58359375,
          "ynorm": 0.621875
        },
        {
          "xnorm": 0.5796875,
          "ynorm": 0.621875
        },
        {
          "xnorm": 0.57421875,
          "ynorm": 0.621875
        },
        {
          "xnorm": 0.56953125,
          "ynorm": 0.6208333333333333
        },
        {
          "xnorm": 0.56484375,
          "ynorm": 0.6197916666666666
        },
        {
          "xnorm": 0.5609375,
          "ynorm": 0.61875
        },
        {
          "xnorm": 0.55703125,
          "ynorm": 0.6177083333333333
        },
        {
          "xnorm": 0.553125,
          "ynorm": 0.6166666666666667
        },
        {
          "xnorm": 0.54921875,
          "ynorm": 0.615625
        },
        {
          "xnorm": 0.5453125,
          "ynorm": 0.615625
        },
        {
          "xnorm": 0.54140625,
          "ynorm": 0.615625
        },
        {
          "xnorm": 0.53671875,
          "ynorm": 0.615625
        },
        {
          "xnorm": 0.53203125,
          "ynorm": 0.615625
        },
        {
          "xnorm": 0.52734375,
          "ynorm": 0.615625
        },
        {
          "xnorm": 0.52265625,
          "ynorm": 0.615625
        },
        {
          "xnorm": 0.51875,
          "ynorm": 0.6145833333333334
        },
        {
          "xnorm": 0.5125,
          "ynorm": 0.6135416666666667
        },
        {
          "xnorm": 0.5078125,
          "ynorm": 0.6135416666666667
        },
        {
          "xnorm": 0.503125,
          "ynorm": 0.6135416666666667
        },
        {
          "xnorm": 0.49765625,
          "ynorm": 0.6135416666666667
        },
        {
          "xnorm": 0.49296875,
          "ynorm": 0.6135416666666667
        },
        {
          "xnorm": 0.4890625,
          "ynorm": 0.6135416666666667
        },
        {
          "xnorm": 0.48515625,
          "ynorm": 0.6135416666666667
        },
        {
          "xnorm": 0.47890625,
          "ynorm": 0.6135416666666667
        },
        {
          "xnorm": 0.475,
          "ynorm": 0.6135416666666667
        },
        {
          "xnorm": 0.4703125,
          "ynorm": 0.6125
        },
        {
          "xnorm": 0.46640625,
          "ynorm": 0.6125
        },
        {
          "xnorm": 0.4609375,
          "ynorm": 0.6125
        },
        {
          "xnorm": 0.45546875,
          "ynorm": 0.6114583333333333
        },
        {
          "xnorm": 0.4515625,
          "ynorm": 0.6114583333333333
        },
        {
          "xnorm": 0.44765625,
          "ynorm": 0.6104166666666667
        },
        {
          "xnorm": 0.44296875,
          "ynorm": 0.6104166666666667
        },
        {
          "xnorm": 0.4375,
          "ynorm": 0.6104166666666667
        },
        {
          "xnorm": 0.4328125,
          "ynorm": 0.6104166666666667
        },
        {
          "xnorm": 0.428125,
          "ynorm": 0.6104166666666667
        },
        {
          "xnorm": 0.4234375,
          "ynorm": 0.6104166666666667
        },
        {
          "xnorm": 0.41875,
          "ynorm": 0.6104166666666667
        },
        {
          "xnorm": 0.41484375,
          "ynorm": 0.6104166666666667
        },
        {
          "xnorm": 0.4109375,
          "ynorm": 0.6104166666666667
        },
        {
          "xnorm": 0.40703125,
          "ynorm": 0.6104166666666667
        },
        {
          "xnorm": 0.403125,
          "ynorm": 0.6104166666666667
        },
        {
          "xnorm": 0.39921875,
          "ynorm": 0.6104166666666667
        },
        {
          "xnorm": 0.3953125,
          "ynorm": 0.6104166666666667
        }
      ],
      "pixel": {
        "regions": [
          [
            [
              [
                294,
                249
              ],
              [
                291,
                250
              ],
              [
                288,
                251
              ],
              [
                285,
                252
              ],
              [
                283,
                252
              ],
              [
                280,
                252
              ],
              [
                278,
                253
              ],
              [
                275,
                253
              ],
              [
                272,
                254
              ],
              [
                269,
                254
              ],
              [
                267,
                255
              ],
              [
                264,
                255
              ],
              [
                261,
                255
              ],
              [
                259,
                256
              ],
              [
                256,
                256
              ],
              [
                253,
                257
              ],
              [
                251,
                257
              ],
              [
                248,
                258
              ],
              [
                244,
                259
              ],
              [
                242,
                259
              ],
              [
                240,
                259
              ],
              [
                237,
                261
              ],
              [
                233,
                262
              ],
              [
                230,
                262
              ],
              [
                228,
                263
              ],
              [
                225,
                264
              ],
              [
                223,
                264
              ],
              [
                220,
                264
              ],
              [
                217,
                264
              ],
              [
                215,
                264
              ],
              [
                212,
                264
              ],
              [
                209,
                265
              ],
              [
                207,
                266
              ],
              [
                204,
                267
              ],
              [
                202,
                269
              ],
              [
                200,
                270
              ],
              [
                197,
                271
              ],
              [
                194,
                272
              ],
              [
                192,
                274
              ],
              [
                189,
                275
              ],
              [
                187,
                276
              ],
              [
                184,
                277
              ],
              [
                181,
                278
              ],
              [
                179,
                280
              ],
              [
                176,
                281
              ],
              [
                174,
                283
              ],
              [
                173,
                285
              ],
              [
                171,
                286
              ],
              [
                169,
                288
              ],
              [
                167,
                290
              ],
              [
                165,
                292
              ],
              [
                164,
                294
              ],
              [
                162,
                296
              ],
              [
                161,
                298
              ],
              [
                160,
                302
              ],
              [
                159,
                305
              ],
              [
                158,
                307
              ],
              [
                158,
                310
              ],
              [
                157,
                314
              ],
              [
                157,
                316
              ],
              [
                158,
                319
              ],
              [
                159,
                322
              ],
              [
                159,
                324
              ],
              [
                161,
                326
              ],
              [
                162,
                329
              ],
              [
                164,
                331
              ],
              [
                165,
                333
              ],
              [
                167,
                334
              ],
              [
                169,
                336
              ],
              [
                171,
                338
              ],
              [
                173,
                340
              ],
              [
                174,
                342
              ],
              [
                176,
                344
              ],
              [
                178,
                346
              ],
              [
                179,
                349
              ],
              [
                181,
                351
              ],
              [
                184,
                352
              ],
              [
                187,
                354
              ],
              [
                189,
                355
              ],
              [
                191,
                356
              ],
              [
                194,
                358
              ],
              [
                196,
                359
              ],
              [
                198,
                361
              ],
              [
                200,
                362
              ],
              [
                203,
                363
              ],
              [
                205,
                365
              ],
              [
                207,
                366
              ],
              [
                210,
                367
              ],
              [
                212,
                369
              ],
              [
                214,
                370
              ],
              [
                217,
                371
              ],
              [
                219,
                373
              ],
              [
                222,
                374
              ],
              [
                224,
                374
              ],
              [
                227,
                375
              ],
              [
                229,
                376
              ],
              [
                232,
                377
              ],
              [
                234,
                378
              ],
              [
                236,
                380
              ],
              [
                239,
                381
              ],
              [
                242,
                382
              ],
              [
                244,
                383
              ],
              [
                246,
                385
              ],
              [
                250,
                386
              ],
              [
                252,
                387
              ],
              [
                255,
                388
              ],
              [
                258,
                389
              ],
              [
                260,
                391
              ],
              [
                262,
                392
              ],
              [
                265,
                393
              ],
              [
                267,
                394
              ],
              [
                270,
                396
              ],
              [
                272,
                397
              ],
              [
                275,
                399
              ],
              [
                277,
                400
              ],
              [
                279,
                402
              ],
              [
                282,
                403
              ],
              [
                284,
                405
              ],
              [
                286,
                406
              ],
              [
                288,
                407
              ],
              [
                290,
                409
              ],
              [
                293,
                409
              ],
              [
                295,
                410
              ],
              [
                298,
                411
              ],
              [
                298,
                409
              ],
              [
                298,
                406
              ],
              [
                298,
                404
              ],
              [
                298,
                401
              ],
              [
                298,
                399
              ],
              [
                298,
                396
              ],
              [
                298,
                393
              ],
              [
                298,
                390
              ],
              [
                298,
                387
              ],
              [
                298,
                385
              ],
              [
                298,
                382
              ],
              [
                298,
                379
              ],
              [
                298,
                376
              ],
              [
                298,
                373
              ],
              [
                298,
                371
              ],
              [
                298,
                367
              ],
              [
                298,
                364
              ],
              [
                297,
                361
              ],
              [
                297,
                359
              ],
              [
                296,
                356
              ],
              [
                296,
                354
              ],
              [
                295,
                351
              ],
              [
                295,
                349
              ],
              [
                295,
                346
              ],
              [
                295,
                343
              ],
              [
                295,
                340
              ],
              [
                295,
                337
              ],
              [
                295,
                334
              ],
              [
                295,
                332
              ],
              [
                294,
                328
              ],
              [
                294,
                325
              ],
              [
                294,
                322
              ],
              [
                294,
                318
              ],
              [
                294,
                315
              ],
              [
                294,
                313
              ],
              [
                294,
                310
              ],
              [
                294,
                306
              ],
              [
                294,
                304
              ],
              [
                294,
                301
              ],
              [
                294,
                298
              ],
              [
                294,
                295
              ],
              [
                293,
                291
              ],
              [
                293,
                289
              ],
              [
                293,
                286
              ],
              [
                293,
                283
              ],
              [
                293,
                280
              ],
              [
                293,
                277
              ],
              [
                293,
                274
              ],
              [
                293,
                271
              ],
              [
                293,
                268
              ],
              [
                293,
                265
              ],
              [
                293,
                263
              ],
              [
                293,
                260
              ],
              [
                293,
                258
              ],
              [
                293,
                255
              ],
              [
                293,
                253
              ]
            ]
          ]
        ],
        "holes": null,
        "imagesize": [
          640,
          480
        ]
      }
    }
  ]
}